pyconwaysgame/args.py
pyconwaysgame/pyconwaysgame.py
pyconwaysgame-2.1.2.dist-info/LICENSE
pyconwaysgame-2.1.2.dist-info/METADATA
pyconwaysgame-2.1.2.dist-info/WHEEL
pyconwaysgame-2.1.2.dist-info/entry_points.txt
pyconwaysgame-2.1.2.dist-info/top_level.txt
pyconwaysgame-2.1.2.dist-info/RECORD
