Metadata-Version: 2.1
Name: pyconwaysgame
Version: 2.1.2
Summary: game of life
Home-page: https://github.com/thib1984/pyconwaysgame
Author: thib1984
Author-email: thibault.garcon@gmail.com
License: MIT
Platform: UNKNOWN
Classifier: Programming Language :: Python :: 3.7
Classifier: Programming Language :: Python :: 3.8
Classifier: Programming Language :: Python :: 3.9
Classifier: Programming Language :: Python :: 3.10
Classifier: Operating System :: MacOS :: MacOS X
Classifier: Operating System :: POSIX
Classifier: Operating System :: Microsoft :: Windows
Classifier: License :: OSI Approved :: MIT License
Requires-Python: >=3.7
License-File: LICENSE
Requires-Dist: columnar
Requires-Dist: click
Requires-Dist: termcolor
Requires-Dist: colorama
